atlasai/vinz/cli/__init__.py
atlasai/vinz/cli/api.py
atlasai/vinz/cli/auth.py
atlasai/vinz/cli/cli.py
atlasai/vinz/cli/config.py
atlasai/vinz/cli/constants.py
atlasai/vinz/cli/options.py
atlasai/vinz/cli/output.py
atlasai/vinz/cli/requests.py
atlasai/vinz/cli/response.py
atlasai/vinz/cli/types.py
atlasai/vinz/cli/utils.py
atlasai/vinz/cli/commands/__init__.py
atlasai/vinz/cli/commands/account.py
atlasai/vinz/cli/commands/api.py
atlasai/vinz/cli/commands/application.py
atlasai/vinz/cli/commands/auth.py
atlasai/vinz/cli/commands/cli.py
atlasai/vinz/cli/commands/config.py
atlasai/vinz/cli/commands/group.py
atlasai/vinz/cli/commands/key.py
atlasai/vinz/cli/commands/organization.py
atlasai/vinz/cli/commands/page.py
atlasai/vinz/cli/commands/role.py
atlasai/vinz/cli/commands/run.py
atlasai/vinz/cli/commands/signup_template.py
atlasai/vinz/cli/commands/user.py
atlasai_vinz_cli-0.0.11.dist-info/METADATA
atlasai_vinz_cli-0.0.11.dist-info/WHEEL
atlasai_vinz_cli-0.0.11.dist-info/entry_points.txt
atlasai_vinz_cli-0.0.11.dist-info/top_level.txt
atlasai_vinz_cli-0.0.11.dist-info/RECORD
